kellyapi/__init__.py
kellyapi/api.py
kellyapi/errors.py
kellyapi-0.0.2.5.dist-info/LICENSE
kellyapi-0.0.2.5.dist-info/METADATA
kellyapi-0.0.2.5.dist-info/WHEEL
kellyapi-0.0.2.5.dist-info/top_level.txt
kellyapi-0.0.2.5.dist-info/RECORD
